unique_queue/__init__.py
unique_queue/unique_queue.py
unique_queue-0.2.1.dist-info/METADATA
unique_queue-0.2.1.dist-info/WHEEL
unique_queue-0.2.1.dist-info/licenses/LICENSE
unique_queue-0.2.1.dist-info/RECORD
