Metadata-Version: 2.1
Name: unique_queue
Version: 0.2.1
Summary: A UniqueQueue class - a FIFO queue, but which ignores attempts to re-add duplicate items, even after they're popped.
Project-URL: Homepage, https://gitopia.com/StudioBreeze/UniqueQueue
Project-URL: Issues, https://gitopia.com/StudioBreeze/UniqueQueue/issues
Project-URL: License, https://gitopia.com/StudioBreeze/UniqueQueue/tree/main/LICENSE
Author-email: StudioBreeze <StudioBreeze+unique_queue@proton.me>
License-File: LICENSE
Classifier: License :: OSI Approved :: MIT License
Classifier: Operating System :: OS Independent
Classifier: Programming Language :: Python :: 3
Requires-Python: >=3.5
